ljc_mcp_server/__init__.py
ljc_mcp_server/__main__.py
ljc_mcp_server/server.py
ljc_mcp_server-0.1.1.dist-info/METADATA
ljc_mcp_server-0.1.1.dist-info/WHEEL
ljc_mcp_server-0.1.1.dist-info/entry_points.txt
ljc_mcp_server-0.1.1.dist-info/top_level.txt
ljc_mcp_server-0.1.1.dist-info/RECORD
