Metadata-Version: 2.4
Name: ljc-mcp-server
Version: 0.1.1
Summary: Add your description here
Requires-Python: >=3.11
Requires-Dist: fastmcp>=2.12.4
